{
    "lobby":{
        "behemoth_slice":{
            "height_start":190,
            "height_end":225,
            "width_start":1475,
            "width_end":1870
        },
        "slice":{
            "height_start":865,
            "height_end":915,
            "width_start":1470,
            "width_end":1780
        },
        "threat_slice":{
            "height_start":263,
            "height_end":298,
            "width_start":1490,
            "width_end":1535
        },
        "hunt_type_slice":{
            "height_start":995,
            "height_end":1045,
            "width_start":730,
            "width_end":1200
        }
    },
    "loot": {
        "behemoth_slice":{
            "height_start":10,
            "height_end":50,
            "width_start":95,
            "width_end":590
        },
        "slice":{
            "height_start":45,
            "height_end":205,
            "width_start":345,
            "width_end":675
        },
        "time_slice":{
            "height_start":55,
            "height_end":80,
            "width_start":220,
            "width_end":305
        },    
        "token_slice":{
            "height_start":274,
            "height_end":899,
            "width_start":90,
            "width_end":165
        }
    },
    "escalation":{
        "lobby_slice":{
            "height_start":120,
            "height_end":185,
            "width_start":1375,
            "width_end":1850
        },
        "summary_slice":{
            "height_start":345,
            "height_end":400,
            "width_start":770,
            "width_end":1150
        },
        "rank_slice":{
            "height_start":590,
            "height_end":670,
            "width_start":1450,
            "width_end":1525
        }
    },
    "bounty":{
        "slice":{
            "height_start":65,
            "height_end":140,
            "width_start":775,
            "width_end":1145
        },
        "quality":{
            "height_start":815,
            "height_end":855,
            "width_start":605,
            "width_end":683
        }
    }
}